CHANGES.txt
COPYRIGHT.txt
LICENSE.txt
README.txt
bootstrap.py
buildout.cfg
setup.py
src/gocept/__init__.py
src/gocept.fixedpoint.egg-info/PKG-INFO
src/gocept.fixedpoint.egg-info/SOURCES.txt
src/gocept.fixedpoint.egg-info/dependency_links.txt
src/gocept.fixedpoint.egg-info/namespace_packages.txt
src/gocept.fixedpoint.egg-info/not-zip-safe
src/gocept.fixedpoint.egg-info/requires.txt
src/gocept.fixedpoint.egg-info/top_level.txt
src/gocept/fixedpoint/README.txt
src/gocept/fixedpoint/__init__.py
src/gocept/fixedpoint/tests.py
