Metadata-Version: 1.0
Name: gocept.fixedpoint
Version: 0.2
Summary: Fixedpoint datatype in python.
Home-page: http://www.python.org/pypi/gocept.fixedpoint
Author: Sebastian Wehrmann
Author-email: sw@gocept.com
License: ZPL 2.1
Keywords: fixedpoint decimal datatype
Platform: UNKNOWN
Classifier: Development Status :: 4 - Beta
Classifier: Environment :: Web Environment
Classifier: Intended Audience :: Developers
Classifier: License :: OSI Approved :: Zope Public License
Classifier: Programming Language :: Python
Classifier: Natural Language :: English
Classifier: Operating System :: OS Independent
Classifier: Topic :: Internet :: WWW/HTTP
